[
    {
        "cat": "laptop",
        "id": 1,
        "marca": "Lenovo",
        "modelo": "Legion 5 Pro",
        "cpu": "INTEL",
        "gpu": "RTX 3080",
        "RAM": 12,
        "disco": 500,
        "precio": 2000,
        "stock": 5,
        "descripcion": "Super Gaming Pc perfecta para jugar todos los juegos de pc del momento",
        "img": "http://localhost:5173/src/imagenes/laptoplenovo1.jpg",
        "oferta": true
    },
    {
        "cat": "laptop",
        "id": 2,
        "marca": "Lenovo",
        "modelo": "Legion 9",
        "cpu": "INTEL",
        "gpu": "RTX 3050",
        "RAM": 16,
        "disco": 700,
        "precio": 1200,
        "stock": 5,
        "descripcion": "Super Gaming Pc perfecta para jugar todos los juegos de pc del momento",
        "img": "http://localhost:5173/src/imagenes/laptoplenovo1.jpg",
        "oferta": true
    },
    {
        "cat": "laptop",
        "id": 3,
        "marca": "Acer",
        "modelo": "Nitro",
        "cpu": "AMD",
        "gpu": "RX 6000",
        "RAM": 16,
        "disco": 500,
        "precio": 1050,
        "stock": 5,
        "descripcion": "Super Gaming Pc perfecta para jugar todos los juegos de pc del momento",
        "img": "http://localhost:5173/src/imagenes/laptop23.jpg",
        "oferta": false
    },
    {
        "cat": "laptop",
        "id": 4,
        "marca": "Asus",
        "modelo": "TUF",
        "cpu": "INTEL",
        "gpu": "RTX 2060",
        "RAM": 32,
        "disco": 1000,
        "precio": 3000,
        "stock": 10,
        "descripcion": "Super Gaming Pc perfecta para jugar todos los juegos de pc del momento",
        "img": "http://localhost:5173/src/imagenes/laptop23.jpg",
        "oferta": true
    },
    {
        "cat": "laptop",
        "id": 5,
        "marca": "Lenovo",
        "modelo": "Alienware",
        "cpu": "INTEL",
        "gpu": "RXT 3080",
        "RAM": 64,
        "disco": 1500,
        "precio": 1400,
        "stock": 2,
        "descripcion": "Super Gaming Pc perfecta para jugar todos los juegos de pc del momento",
        "img": "http://localhost:5173/src/imagenes/laptoplenovo1.jpg",
        "oferta": false
    },
    {
        "cat": "laptop",
        "id": 6,
        "marca": "MSI",
        "modelo": "GF63",
        "cpu": "INTEL",
        "gpu": "RXT 3050TI",
        "RAM": 8,
        "disco": 500,
        "precio": 7000,
        "stock": 5,
        "descripcion": "Super Gaming Pc perfecta para jugar todos los juegos de pc del momento",
        "img": "http://localhost:5173/src/imagenes/laptoplenovo1.jpg",
        "oferta": false
    },
    {
        "cat": "laptop",
        "id": 7,
        "marca": "MSI",
        "modelo": "GF100",
        "cpu": "INTEL",
        "gpu": "RXT 3080TI",
        "RAM": 24,
        "disco": 1000,
        "precio": 800,
        "stock": 0,
        "descripcion": "Super Gaming Pc perfecta para jugar todos los juegos de pc del momento",
        "img": "http://localhost:5173/src/imagenes/laptoplenovo1.jpg",
        "oferta": false
    },
    {
        "cat": "laptop",
        "id": 8,
        "marca": "Hp",
        "modelo": "Victus",
        "cpu": "INTEL",
        "gpu": "RXT 2080",
        "RAM": 32,
        "disco": 1224,
        "precio": 1100,
        "stock": 0,
        "descripcion": "Super Gaming Pc perfecta para jugar todos los juegos de pc del momento",
        "img": "http://localhost:5173/src/imagenes/laptoplenovo1.jpg",
        "oferta": false
    },
    {
        "cat": "laptop",
        "id": 9,
        "marca": "Asus",
        "modelo": "Republic of Gamers",
        "cpu": "AMD",
        "gpu": "RXT 3080",
        "RAM": 16,
        "disco": 1500,
        "precio": 500,
        "stock": 0,
        "descripcion": "Super Gaming Pc perfecta para jugar todos los juegos de pc del momento",
        "img": "http://localhost:5173/src/imagenes/laptoplenovo1.jpg",
        "oferta": false
    },
    {
        "cat": "laptop",
        "id": 10,
        "marca": "Asus",
        "modelo": "Moder",
        "cpu": "AMD",
        "gpu": "RXT 1660",
        "RAM": 8,
        "disco": 1500,
        "precio": 2500,
        "stock": 1,
        "descripcion": "Super Gaming Pc perfecta para jugar todos los juegos de pc del momento",
        "img": "http://localhost:5173/src/imagenes/laptoplenovo1.jpg",
        "oferta": false
    },
    {
        "cat": "laptop",
        "id": 11,
        "marca": "Dell",
        "modelo": "Nose",
        "cpu": "AMD",
        "gpu": "RXT 1050",
        "RAM": 12,
        "disco": 1500,
        "precio": 2600,
        "stock": 3,
        "descripcion": "Super Gaming Pc perfecta para jugar todos los juegos de pc del momento",
        "img": "http://localhost:5173/src/imagenes/laptoplenovo1.jpg",
        "oferta": false
    },
    {
        "cat": "laptop",
        "id": 12,
        "marca": "Dell",
        "modelo": "Precision",
        "cpu": "INTEL",
        "gpu": "RXT 1660",
        "RAM": 4,
        "disco": 500,
        "precio": 900,
        "stock": 1,
        "descripcion": "Super Gaming Pc perfecta para jugar todos los juegos de pc del momento",
        "img": "http://localhost:5173/src/imagenes/laptoplenovo1.jpg",
        "oferta": false
    },
    {
        "cat": "monitor",
        "id": 13,
        "marca": "Samsung",
        "modelo": "F390 24'",
        "precio": 269,
        "stock": 4,
        "descripcion": "Disfrutá de una experiencia totalmente inmersiva con el nuevo monitor Samsung con pantalla LED curva Full HD de 24’",
        "img": "http://localhost:5173/src/imagenes/monitorSamsung.jpg",
        "oferta": false,
        "cpu": "N/A"
    },
    {
        "cat": "monitor",
        "id": 14,
        "marca": "LG",
        "modelo": "LG 24'",
        "precio": 119,
        "stock": 4,
        "descripcion": "Con su diseño sin bordes, este monitor te brinda la mejor experiencia de juego.",
        "img": "http://localhost:5173/src/imagenes/monitorLG.jpg",
        "cpu": "N/A",
        "oferta": true
    },
    {
        "cat": "monitor",
        "id": 15,
        "marca": "Xiaomi",
        "modelo": "1C 23.8”",
        "precio": 300,
        "stock": 4,
        "descripcion": "Con su diseño sin bordes, este monitor te brinda la mejor experiencia de juego.",
        "img": "http://localhost:5173/src/imagenes/monitorxiaomi.jpg",
        "cpu": "N/A",
        "oferta": false
    },
    {
        "cat": "monitor",
        "id": 16,
        "marca": "JVC",
        "modelo": "jvc curvo 32'",
        "precio": 269,
        "stock": 4,
        "descripcion": "Con su diseño sin bordes, este monitor te brinda la mejor experiencia de juego.",
        "img": "http://localhost:5173/src/imagenes/monitorJVC.jpg",
        "cpu": "N/A",
        "oferta": false
    },
    {
        "cat": "grafica",
        "id": 17,
        "marca": "NVIDIA",
        "modelo": "RTX 2060",
        "precio": 700,
        "stock": 3,
        "descripcion": "Ideal para gaming",
        "img": "http://localhost:5173/src/imagenes/nvidiartx2060.jpg",
        "cpu": "N/A",
        "oferta": true
    },
    {
        "cat": "grafica",
        "id": 18,
        "marca": "NVIDIA",
        "modelo": "RTX 2070",
        "precio": 800,
        "stock": 4,
        "descripcion": "Ideal para gaming",
        "img": "http://localhost:5173/src/imagenes/nvidia3.jpg",
        "cpu": "N/A",
        "oferta": false
    },
    {
        "cat": "grafica",
        "id": 19,
        "marca": "NVIDIA",
        "modelo": "RTX 2080",
        "precio": 900,
        "stock": 1,
        "descripcion": "Ideal para gaming",
        "img": "http://localhost:5173/src/imagenes/nvidia.jpg",
        "cpu": "N/A",
        "oferta": false
    },
    {
        "cat": "grafica",
        "id": 20,
        "marca": "RADEON",
        "modelo": "RX560",
        "precio": 1050,
        "stock": 1,
        "descripcion": "Ideal para gaming",
        "img": "http://localhost:5173/src/imagenes/Radeonrx560.jpg",
        "cpu": "N/A",
        "oferta": false
    },
    {
        "cat": "grafica",
        "id": 21,
        "marca": "RADEON",
        "modelo": "RX 6400",
        "precio": 900,
        "stock": 6,
        "descripcion": "Ideal para gaming",
        "img": "http://localhost:5173/src/imagenes/Radeonrx550.jpg",
        "cpu": "N/A",
        "oferta": false
    },
    {
        "cat": "grafica",
        "id": 22,
        "marca": "RADEON",
        "modelo": "RX 6500",
        "precio": 750,
        "stock": 12,
        "descripcion": "Ideal para gaming",
        "img": "http://localhost:5173/src/imagenes/Radeonrx550.jpg",
        "cpu": "N/A",
        "oferta": true
    },
    {
        "cat": "accesorios",
        "id": 23,
        "marca": "XtrikeMe",
        "precio": 40,
        "stock": 7,
        "descripcion": "Teclado Rgba",
        "img": "http://localhost:5173/src/imagenes/teclado.jpg",
        "cpu": "N/A",
        "oferta": true
    },
    {
        "cat": "accesorios",
        "id": 24,
        "marca": "Xtreme",
        "precio": 40,
        "stock": 7,
        "descripcion": "Auriculares",
        "img": "http://localhost:5173/src/imagenes/auriculares.jpg",
        "cpu": "N/A",
        "oferta": false
    }
]